ivanbicalho/__init__.py
ivanbicalho/notifications.py
ivanbicalho_notifications-0.0.4.dist-info/LICENSE
ivanbicalho_notifications-0.0.4.dist-info/METADATA
ivanbicalho_notifications-0.0.4.dist-info/WHEEL
ivanbicalho_notifications-0.0.4.dist-info/top_level.txt
ivanbicalho_notifications-0.0.4.dist-info/RECORD
