Metadata-Version: 2.1
Name: ivanbicalho-notifications
Version: 0.0.4
Summary: Package to send email notifications specifically for ivanbicalho projects
Home-page: https://github.com/ivanbicalho
Author: Ivan Bicalho
Author-email: ivanribeirob@gmail.com
License: UNKNOWN
Platform: UNKNOWN
Classifier: Programming Language :: Python :: 3
Classifier: License :: OSI Approved :: MIT License
Classifier: Operating System :: OS Independent
Requires-Python: >=3.6
License-File: LICENSE
